gs_pip_install/__init__.py
gs_pip_install/gs_pip_install.py
gs_pip_install-0.2.6.dist-info/LICENSE
gs_pip_install-0.2.6.dist-info/METADATA
gs_pip_install-0.2.6.dist-info/WHEEL
gs_pip_install-0.2.6.dist-info/entry_points.txt
gs_pip_install-0.2.6.dist-info/top_level.txt
gs_pip_install-0.2.6.dist-info/RECORD
