Metadata-Version: 2.1
Name: gs-pip-install
Version: 0.2.6
Summary: Pip Install Packages Stored in Google Cloud Buckets
Home-page: https://github.com/lucidsushi/gs_pip_install
Author: David Su
Author-email: contact@davidsushi.com
License: MIT license
Keywords: gs_pip_install
Platform: UNKNOWN
Classifier: Development Status :: 2 - Pre-Alpha
Classifier: Intended Audience :: Developers
Classifier: License :: OSI Approved :: MIT License
Classifier: Natural Language :: English
Classifier: Programming Language :: Python :: 2.7
Classifier: Programming Language :: Python :: 3
Classifier: Programming Language :: Python :: 3.5
Classifier: Programming Language :: Python :: 3.6
Classifier: Programming Language :: Python :: 3.7
Classifier: Programming Language :: Python :: 3.8
Requires-Python: >=2.7
License-File: LICENSE
Requires-Dist: Click (==7.1.2)
Requires-Dist: google-cloud-storage (==1.42.2)
